odoo/addons/website_sale_product_attribute_filter_category/README.rst
odoo/addons/website_sale_product_attribute_filter_category/__init__.py
odoo/addons/website_sale_product_attribute_filter_category/__manifest__.py
odoo/addons/website_sale_product_attribute_filter_category/controllers/__init__.py
odoo/addons/website_sale_product_attribute_filter_category/controllers/main.py
odoo/addons/website_sale_product_attribute_filter_category/i18n/ca.po
odoo/addons/website_sale_product_attribute_filter_category/i18n/es.po
odoo/addons/website_sale_product_attribute_filter_category/i18n/fi.po
odoo/addons/website_sale_product_attribute_filter_category/i18n/it.po
odoo/addons/website_sale_product_attribute_filter_category/i18n/nl.po
odoo/addons/website_sale_product_attribute_filter_category/i18n/website_sale_product_attribute_filter_category.pot
odoo/addons/website_sale_product_attribute_filter_category/models/__init__.py
odoo/addons/website_sale_product_attribute_filter_category/models/product_attribute_category.py
odoo/addons/website_sale_product_attribute_filter_category/readme/CONFIGURE.md
odoo/addons/website_sale_product_attribute_filter_category/readme/CONTRIBUTORS.md
odoo/addons/website_sale_product_attribute_filter_category/readme/DESCRIPTION.md
odoo/addons/website_sale_product_attribute_filter_category/readme/USAGE.md
odoo/addons/website_sale_product_attribute_filter_category/static/description/icon.png
odoo/addons/website_sale_product_attribute_filter_category/static/description/index.html
odoo/addons/website_sale_product_attribute_filter_category/static/src/scss/website_sale_attribute_filter_category.scss
odoo/addons/website_sale_product_attribute_filter_category/static/tests/tours/website_sale_attribute_filter_category_tour.esm.js
odoo/addons/website_sale_product_attribute_filter_category/tests/__init__.py
odoo/addons/website_sale_product_attribute_filter_category/tests/test_website_sale_product_attribute_filter_category.py
odoo_addon_website_sale_product_attribute_filter_category-17.0.1.0.0.4.dist-info/METADATA
odoo_addon_website_sale_product_attribute_filter_category-17.0.1.0.0.4.dist-info/WHEEL
odoo_addon_website_sale_product_attribute_filter_category-17.0.1.0.0.4.dist-info/top_level.txt
odoo_addon_website_sale_product_attribute_filter_category-17.0.1.0.0.4.dist-info/RECORD
